{
  "verbs": [
    {
      "infinitive": "être",
      "conjugations": {
        "présent": {
          "je": "suis",
          "tu": "es",
          "il/elle": "est",
          "nous": "sommes",
          "vous": "êtes",
          "ils/elles": "sont"
        },
        "passé composé": {
          "j'": "ai été",
          "tu": "as été",
          "il/elle": "a été",
          "nous": "avons été",
          "vous": "avez été",
          "ils/elles": "ont été"
        },
        "imparfait": {
          "j'": "étais",
          "tu": "étais",
          "il/elle": "était",
          "nous": "étions",
          "vous": "étiez",
          "ils/elles": "étaient"
        },
        "passé simple": {
          "je": "fus",
          "tu": "fus",
          "il/elle": "fut",
          "nous": "fûmes",
          "vous": "fûtes",
          "ils/elles": "furent"
        },
        "futur simple": {
          "je": "serai",
          "tu": "seras",
          "il/elle": "sera",
          "nous": "serons",
          "vous": "serez",
          "ils/elles": "seront"
        },
        "imparfait du subjonctif": {
          "que je": "fusse",
          "que tu": "fusses",
          "qu'il/elle": "fût",
          "que nous": "fussions",
          "que vous": "fussiez",
          "qu'ils/elles": "fussent"
        },
        "subjonctif passé": {
          "que j'": "aie été",
          "que tu": "aies été",
          "qu'il/elle": "ait été",
          "que nous": "ayons été",
          "que vous": "ayez été",
          "qu'ils/elles": "aient été"
        },
        "conditionnel présent": {
          "je": "serais",
          "tu": "serais",
          "il/elle": "serait",
          "nous": "serions",
          "vous": "seriez",
          "ils/elles": "seraient"
        },
        "plus-que-parfait": {
          "j'": "avais été",
          "tu": "avais été",
          "il/elle": "avait été",
          "nous": "avions été",
          "vous": "aviez été",
          "ils/elles": "avaient été"
        },
        "passé antérieur": {
          "j'": "eus été",
          "tu": "eus été",
          "il/elle": "eut été",
          "nous": "eûmes été",
          "vous": "eûtes été",
          "ils/elles": "eurent été"
        },
        "futur antérieur": {
          "j'": "aurai été",
          "tu": "auras été",
          "il/elle": "aura été",
          "nous": "aurons été",
          "vous": "aurez été",
          "ils/elles": "auront été"
        },
        "conditionnel passé première forme": {
          "j'": "aurais été",
          "tu": "aurais été",
          "il/elle": "aurait été",
          "nous": "aurions été",
          "vous": "auriez été",
          "ils/elles": "auraient été"
        }
      }
    },
	{
      "infinitive": "marcher",
      "conjugations": {
        "présent": {
          "je": "marche",
          "tu": "marches",
          "il/elle": "marche",
          "nous": "marchons",
          "vous": "marchez",
          "ils/elles": "marchent"
        },
        "passé composé": {
          "j'": "ai marché",
          "tu": "as marché",
          "il/elle": "a marché",
          "nous": "avons marché",
          "vous": "avez marché",
          "ils/elles": "ont marché"
        },
        "imparfait": {
          "je": "marchais",
          "tu": "marchais",
          "il/elle": "marchait",
          "nous": "marchions",
          "vous": "marchiez",
          "ils/elles": "marchaient"
        },
        "passé simple": {
          "je": "marchai",
          "tu": "marchas",
          "il/elle": "marcha",
          "nous": "marchâmes",
          "vous": "marchâtes",
          "ils/elles": "marchèrent"
        },
        "futur simple": {
          "je": "marcherai",
          "tu": "marcheras",
          "il/elle": "marchera",
          "nous": "marcherons",
          "vous": "marcherez",
          "ils/elles": "marcheront"
        },
        "imparfait du subjonctif": {
          "que je": "marchasse",
          "que tu": "marchasses",
          "qu'il/elle": "marchât",
          "que nous": "marchassions",
          "que vous": "marchassiez",
          "qu'ils/elles": "marchassent"
        },
        "subjonctif passé": {
          "que j'": "aie marché",
          "que tu": "aies marché",
          "qu'il/elle": "ait marché",
          "que nous": "ayons marché",
          "que vous": "ayez marché",
          "qu'ils/elles": "aient marché"
        },
        "conditionnel présent": {
          "je": "marcherais",
          "tu": "marcherais",
          "il/elle": "marcherait",
          "nous": "marcherions",
          "vous": "marcheriez",
          "ils/elles": "marcheraient"
        },
        "plus-que-parfait": {
          "j'": "avais marché",
          "tu": "avais marché",
          "il/elle": "avait marché",
          "nous": "avions marché",
          "vous": "aviez marché",
          "ils/elles": "avaient marché"
        },
        "passé antérieur": {
          "j'": "eus marché",
          "tu": "eus marché",
          "il/elle": "eut marché",
          "nous": "eûmes marché",
          "vous": "eûtes marché",
          "ils/elles": "eurent marché"
        },
        "futur antérieur": {
          "j'": "aurai marché",
          "tu": "auras marché",
          "il/elle": "aura marché",
          "nous": "aurons marché",
          "vous": "aurez marché",
          "ils/elles": "auront marché"
        },
        "conditionnel passé première forme": {
          "j'": "aurais marché",
          "tu": "aurais marché",
          "il/elle": "aurait marché",
          "nous": "aurions marché",
          "vous": "auriez marché",
          "ils/elles": "auraient marché"
        }
      }
    },
    {
      "infinitive": "pousser",
      "conjugations": {
        "présent": {
          "je": "pousse",
          "tu": "pousses",
          "il/elle": "pousse",
          "nous": "poussons",
          "vous": "poussez",
          "ils/elles": "poussent"
        },
        "passé composé": {
          "j'": "ai poussé",
          "tu": "as poussé",
          "il/elle": "a poussé",
          "nous": "avons poussé",
          "vous": "avez poussé",
          "ils/elles": "ont poussé"
        },
        "imparfait": {
          "je": "poussais",
          "tu": "poussais",
          "il/elle": "poussait",
          "nous": "poussions",
          "vous": "poussiez",
          "ils/elles": "poussaient"
        },
        "passé simple": {
          "je": "poussai",
          "tu": "poussas",
          "il/elle": "poussa",
          "nous": "poussâmes",
          "vous": "poussâtes",
          "ils/elles": "poussèrent"
        },
        "futur simple": {
          "je": "pousserai",
          "tu": "pousseras",
          "il/elle": "poussera",
          "nous": "pousserons",
          "vous": "pousserez",
          "ils/elles": "pousseront"
        },
        "imparfait du subjonctif": {
          "que je": "poussasse",
          "que tu": "poussasses",
          "qu'il/elle": "poussât",
          "que nous": "poussassions",
          "que vous": "poussassiez",
          "qu'ils/elles": "poussassent"
        },
        "subjonctif passé": {
          "que j'": "aie poussé",
          "que tu": "aies poussé",
          "qu'il/elle": "ait poussé",
          "que nous": "ayons poussé",
          "que vous": "ayez poussé",
          "qu'ils/elles": "aient poussé"
        },
        "conditionnel présent": {
          "je": "pousserais",
          "tu": "pousserais",
          "il/elle": "pousserait",
          "nous": "pousserions",
          "vous": "pousseriez",
          "ils/elles": "pousseraient"
        },
        "plus-que-parfait": {
          "j'": "avais poussé",
          "tu": "avais poussé",
          "il/elle": "avait poussé",
          "nous": "avions poussé",
          "vous": "aviez poussé",
          "ils/elles": "avaient poussé"
        },
        "passé antérieur": {
          "j'": "eus poussé",
          "tu": "eus poussé",
          "il/elle": "eut poussé",
          "nous": "eûmes poussé",
          "vous": "eûtes poussé",
          "ils/elles": "eurent poussé"
        },
        "futur antérieur": {
          "j'": "aurai poussé",
          "tu": "auras poussé",
          "il/elle": "aura poussé",
          "nous": "aurons poussé",
          "vous": "aurez poussé",
          "ils/elles": "auront poussé"
        },
        "conditionnel passé première forme": {
          "j'": "aurais poussé",
          "tu": "aurais poussé",
          "il/elle": "aurait poussé",
          "nous": "aurions poussé",
          "vous": "auriez poussé",
          "ils/elles": "auraient poussé"
        }
      }
    },
    {
      "infinitive": "couper",
      "conjugations": {
        "présent": {
          "je": "coupe",
          "tu": "coupes",
          "il/elle": "coupe",
          "nous": "coupons",
          "vous": "coupez",
          "ils/elles": "coupent"
        },
        "passé composé": {
          "j'": "ai coupé",
          "tu": "as coupé",
          "il/elle": "a coupé",
          "nous": "avons coupé",
          "vous": "avez coupé",
          "ils/elles": "ont coupé"
        },
        "imparfait": {
          "je": "coupais",
          "tu": "coupais",
          "il/elle": "coupait",
          "nous": "coupions",
          "vous": "coupiez",
          "ils/elles": "coupaient"
        },
        "passé simple": {
          "je": "coupai",
          "tu": "coupas",
          "il/elle": "coupa",
          "nous": "coupâmes",
          "vous": "coupâtes",
          "ils/elles": "coupèrent"
        },
        "futur simple": {
          "je": "couperai",
          "tu": "couperas",
          "il/elle": "coupera",
          "nous": "couperons",
          "vous": "couperez",
          "ils/elles": "couperont"
        },
        "imparfait du subjonctif": {
          "que je": "coupasse",
          "que tu": "coupasses",
          "qu'il/elle": "coupât",
          "que nous": "coupassions",
          "que vous": "coupassiez",
          "qu'ils/elles": "coupassent"
        },
        "subjonctif passé": {
          "que j'": "aie coupé",
          "que tu": "aies coupé",
          "qu'il/elle": "ait coupé",
          "que nous": "ayons coupé",
          "que vous": "ayez coupé",
          "qu'ils/elles": "aient coupé"
        },
        "conditionnel présent": {
          "je": "couperais",
          "tu": "couperais",
          "il/elle": "couperait",
          "nous": "couperions",
          "vous": "couperiez",
          "ils/elles": "couperaient"
        },
        "plus-que-parfait": {
          "j'": "avais coupé",
          "tu": "avais coupé",
          "il/elle": "avait coupé",
          "nous": "avions coupé",
          "vous": "aviez coupé",
          "ils/elles": "avaient coupé"
        },
        "passé antérieur": {
          "j'": "eus coupé",
          "tu": "eus coupé",
          "il/elle": "eut coupé",
          "nous": "eûmes coupé",
          "vous": "eûtes coupé",
          "ils/elles": "eurent coupé"
        },
        "futur antérieur": {
          "j'": "aurai coupé",
          "tu": "auras coupé",
          "il/elle": "aura coupé",
          "nous": "aurons coupé",
          "vous": "aurez coupé",
          "ils/elles": "auront coupé"
        },
        "conditionnel passé première forme": {
          "j'": "aurais coupé",
          "tu": "aurais coupé",
          "il/elle": "aurait coupé",
          "nous": "aurions coupé",
          "vous": "auriez coupé",
          "ils/elles": "auraient coupé"
        }
      }
    },
    {
      "infinitive": "danser",
      "conjugations": {
        "présent": {
          "je": "danse",
          "tu": "danses",
          "il/elle": "danse",
          "nous": "dansons",
          "vous": "dansez",
          "ils/elles": "dansent"
        },
        "passé composé": {
          "j'": "ai dansé",
          "tu": "as dansé",
          "il/elle": "a dansé",
          "nous": "avons dansé",
          "vous": "avez dansé",
          "ils/elles": "ont dansé"
        },
        "imparfait": {
          "je": "dansais",
          "tu": "dansais",
          "il/elle": "dansait",
          "nous": "dansions",
          "vous": "dansiez",
          "ils/elles": "dansaient"
        },
        "passé simple": {
          "je": "dansai",
          "tu": "dansas",
          "il/elle": "dansa",
          "nous": "dansâmes",
          "vous": "dansâtes",
          "ils/elles": "dansèrent"
        },
        "futur simple": {
          "je": "danserai",
          "tu": "danseras",
          "il/elle": "dansera",
          "nous": "danserons",
          "vous": "danserez",
          "ils/elles": "danseront"
        },
        "imparfait du subjonctif": {
          "que je": "dansasse",
          "que tu": "dansasses",
          "qu'il/elle": "dansât",
          "que nous": "dansassions",
          "que vous": "dansassiez",
          "qu'ils/elles": "dansassent"
        },
        "subjonctif passé": {
          "que j'": "aie dansé",
          "que tu": "aies dansé",
          "qu'il/elle": "ait dansé",
          "que nous": "ayons dansé",
          "que vous": "ayez dansé",
          "qu'ils/elles": "aient dansé"
        },
        "conditionnel présent": {
          "je": "danserais",
          "tu": "danserais",
          "il/elle": "danserait",
          "nous": "danserions",
          "vous": "danseriez",
          "ils/elles": "danseraient"
        },
        "plus-que-parfait": {
          "j'": "avais dansé",
          "tu": "avais dansé",
          "il/elle": "avait dansé",
          "nous": "avions dansé",
          "vous": "aviez dansé",
          "ils/elles": "avaient dansé"
        },
        "passé antérieur": {
          "j'": "eus dansé",
          "tu": "eus dansé",
          "il/elle": "eut dansé",
          "nous": "eûmes dansé",
          "vous": "eûtes dansé",
          "ils/elles": "eurent dansé"
        },
        "futur antérieur": {
          "j'": "aurai dansé",
          "tu": "auras dansé",
          "il/elle": "aura dansé",
          "nous": "aurons dansé",
          "vous": "aurez dansé",
          "ils/elles": "auront dansé"
        },
        "conditionnel passé première forme": {
          "j'": "aurais dansé",
          "tu": "aurais dansé",
          "il/elle": "aurait dansé",
          "nous": "aurions dansé",
          "vous": "auriez dansé",
          "ils/elles": "auraient dansé"
        }
      }
    },
    {
      "infinitive": "avoir",
      "conjugations": {
        "présent": {
          "j'": "ai",
          "tu": "as",
          "il/elle": "a",
          "nous": "avons",
          "vous": "avez",
          "ils/elles": "ont"
        },
        "passé composé": {
          "j'": "ai eu",
          "tu": "as eu",
          "il/elle": "a eu",
          "nous": "avons eu",
          "vous": "avez eu",
          "ils/elles": "ont eu"
        },
        "imparfait": {
          "j'": "avais",
          "tu": "avais",
          "il/elle": "avait",
          "nous": "avions",
          "vous": "aviez",
          "ils/elles": "avaient"
        },
        "passé simple": {
          "j'": "eus",
          "tu": "eus",
          "il/elle": "eut",
          "nous": "eûmes",
          "vous": "eûtes",
          "ils/elles": "eurent"
        },
        "futur simple": {
          "j'": "aurai",
          "tu": "auras",
          "il/elle": "aura",
          "nous": "aurons",
          "vous": "aurez",
          "ils/elles": "auront"
        },
        "imparfait du subjonctif": {
          "que j'": "eusse",
          "que tu": "eusses",
          "qu'il/elle": "eût",
          "que nous": "eussions",
          "que vous": "eussiez",
          "qu'ils/elles": "eussent"
        },
        "subjonctif passé": {
          "que j'": "aie eu",
          "que tu": "aies eu",
          "qu'il/elle": "ait eu",
          "que nous": "ayons eu",
          "que vous": "ayez eu",
          "qu'ils/elles": "aient eu"
        },
        "conditionnel présent": {
          "j'": "aurais",
          "tu": "aurais",
          "il/elle": "aurait",
          "nous": "aurions",
          "vous": "auriez",
          "ils/elles": "auraient"
        },
        "plus-que-parfait": {
          "j'": "avais eu",
          "tu": "avais eu",
          "il/elle": "avait eu",
          "nous": "avions eu",
          "vous": "aviez eu",
          "ils/elles": "avaient eu"
        },
        "passé antérieur": {
          "j'": "eus eu",
          "tu": "eus eu",
          "il/elle": "eut eu",
          "nous": "eûmes eu",
          "vous": "eûtes eu",
          "ils/elles": "eurent eu"
        },
        "futur antérieur": {
          "j'": "aurai eu",
          "tu": "auras eu",
          "il/elle": "aura eu",
          "nous": "aurons eu",
          "vous": "aurez eu",
          "ils/elles": "auront eu"
        },
        "conditionnel passé première forme": {
          "j'": "aurais eu",
          "tu": "aurais eu",
          "il/elle": "aurait eu",
          "nous": "aurions eu",
          "vous": "auriez eu",
          "ils/elles": "auraient eu"
        }
      }
    },
    {
      "infinitive": "aller",
      "conjugations": {
        "présent": {
          "je": "vais",
          "tu": "vas",
          "il/elle": "va",
          "nous": "allons",
          "vous": "allez",
          "ils/elles": "vont"
        },
        "passé composé": {
          "je": "suis allé",
          "tu": "es allé",
          "il/elle": "est allé",
          "nous": "sommes allés",
          "vous": "êtes allés",
          "ils/elles": "sont allés"
        },
        "imparfait": {
          "j'": "allais",
          "tu": "allais",
          "il/elle": "allait",
          "nous": "allions",
          "vous": "alliez",
          "ils/elles": "allaient"
        },
        "passé simple": {
          "j'": "allai",
          "tu": "allas",
          "il/elle": "alla",
          "nous": "allâmes",
          "vous": "allâtes",
          "ils/elles": "allèrent"
        },
        "futur simple": {
          "j'": "irai",
          "tu": "iras",
          "il/elle": "ira",
          "nous": "irons",
          "vous": "irez",
          "ils/elles": "iront"
        },
        "imparfait du subjonctif": {
          "que j'": "allasse",
          "que tu": "allasses",
          "qu'il/elle": "allât",
          "que nous": "allassions",
          "que vous": "allassiez",
          "qu'ils/elles": "allassent"
        },
        "subjonctif passé": {
          "que je": "sois allé",
          "que tu": "sois allé",
          "qu'il/elle": "soit allé",
          "que nous": "soyons allés",
          "que vous": "soyez allés",
          "qu'ils/elles": "soient allés"
        },
        "conditionnel présent": {
          "j'": "irais",
          "tu": "irais",
          "il/elle": "irait",
          "nous": "irions",
          "vous": "iriez",
          "ils/elles": "iraient"
        },
        "plus-que-parfait": {
          "j'": "étais allé",
          "tu": "étais allé",
          "il/elle": "était allé",
          "nous": "étions allés",
          "vous": "étiez allés",
          "ils/elles": "étaient allés"
        },
        "passé antérieur": {
          "je": "fus allé",
          "tu": "fus allé",
          "il/elle": "fut allé",
          "nous": "fûmes allés",
          "vous": "fûtes allés",
          "ils/elles": "furent allés"
        },
        "futur antérieur": {
          "je": "serai allé",
          "tu": "seras allé",
          "il/elle": "sera allé",
          "nous": "serons allés",
          "vous": "serez allés",
          "ils/elles": "seront allés"
        },
        "conditionnel passé première forme": {
          "je": "serais allé",
          "tu": "serais allé",
          "il/elle": "serait allé",
          "nous": "serions allés",
          "vous": "seriez allés",
          "ils/elles": "seraient allés"
        }
      }
    },
    {
      "infinitive": "faire",
      "conjugations": {
        "présent": {
          "je": "fais",
          "tu": "fais",
          "il/elle": "fait",
          "nous": "faisons",
          "vous": "faites",
          "ils/elles": "font"
        },
        "passé composé": {
          "je": "ai fait",
          "tu": "as fait",
          "il/elle": "a fait",
          "nous": "avons fait",
          "vous": "avez fait",
          "ils/elles": "ont fait"
        },
        "imparfait": {
          "je": "faisais",
          "tu": "faisais",
          "il/elle": "faisait",
          "nous": "faisions",
          "vous": "faisiez",
          "ils/elles": "faisaient"
        },
        "passé simple": {
          "je": "fis",
          "tu": "fis",
          "il/elle": "fit",
          "nous": "fîmes",
          "vous": "fîtes",
          "ils/elles": "firent"
        },
        "futur simple": {
          "je": "ferai",
          "tu": "feras",
          "il/elle": "fera",
          "nous": "ferons",
          "vous": "ferez",
          "ils/elles": "feront"
        },
        "imparfait du subjonctif": {
          "que je": "fisse",
          "que tu": "fisses",
          "qu'il/elle": "fît",
          "que nous": "fissions",
          "que vous": "fissiez",
          "qu'ils/elles": "fissent"
        },
        "subjonctif passé": {
          "que j'": "aie fait",
          "que tu": "aies fait",
          "qu'il/elle": "ait fait",
          "que nous": "ayons fait",
          "que vous": "ayez fait",
          "qu'ils/elles": "aient fait"
        },
        "conditionnel présent": {
          "je": "ferais",
          "tu": "ferais",
          "il/elle": "ferait",
          "nous": "ferions",
          "vous": "feriez",
          "ils/elles": "feraient"
        },
        "plus-que-parfait": {
          "j'": "avais fait",
          "tu": "avais fait",
          "il/elle": "avait fait",
          "nous": "avions fait",
          "vous": "aviez fait",
          "ils/elles": "avaient fait"
        },
        "passé antérieur": {
          "j'": "eus fait",
          "tu": "eus fait",
          "il/elle": "eut fait",
          "nous": "eûmes fait",
          "vous": "eûtes fait",
          "ils/elles": "eurent fait"
        },
        "futur antérieur": {
          "je": "aurai fait",
          "tu": "auras fait",
          "il/elle": "aura fait",
          "nous": "aurons fait",
          "vous": "aurez fait",
          "ils/elles": "auront fait"
        },
        "conditionnel passé première forme": {
          "j'": "aurais fait",
          "tu": "aurais fait",
          "il/elle": "aurait fait",
          "nous": "aurions fait",
          "vous": "auriez fait",
          "ils/elles": "auraient fait"
        }
      }
    },
	 {
      "infinitive": "voir",
      "conjugations": {
        "présent": {
          "je": "vois",
          "tu": "vois",
          "il/elle": "voit",
          "nous": "voyons",
          "vous": "voyez",
          "ils/elles": "voient"
        },
        "passé composé": {
          "j'": "ai vu",
          "tu": "as vu",
          "il/elle": "a vu",
          "nous": "avons vu",
          "vous": "avez vu",
          "ils/elles": "ont vu"
        },
        "imparfait": {
          "je": "voyais",
          "tu": "voyais",
          "il/elle": "voyait",
          "nous": "voyions",
          "vous": "voyiez",
          "ils/elles": "voyaient"
        },
        "passé simple": {
          "je": "vis",
          "tu": "vis",
          "il/elle": "vit",
          "nous": "vîmes",
          "vous": "vîtes",
          "ils/elles": "virent"
        },
        "futur simple": {
          "je": "verrai",
          "tu": "verras",
          "il/elle": "verra",
          "nous": "verrons",
          "vous": "verrez",
          "ils/elles": "verront"
        },
        "imparfait du subjonctif": {
          "que je": "visse",
          "que tu": "visses",
          "qu’il/elle": "vît",
          "que nous": "vissions",
          "que vous": "vissiez",
          "qu’ils/elles": "vissent"
        },
        "subjonctif passé": {
          "que j'": "aie vu",
          "que tu": "aies vu",
          "qu’il/elle": "ait vu",
          "que nous": "ayons vu",
          "que vous": "ayez vu",
          "qu’ils/elles": "aient vu"
        },
        "conditionnel présent": {
          "je": "verrais",
          "tu": "verrais",
          "il/elle": "verrait",
          "nous": "verrions",
          "vous": "verriez",
          "ils/elles": "verraient"
        },
        "plus-que-parfait": {
          "j'": "avais vu",
          "tu": "avais vu",
          "il/elle": "avait vu",
          "nous": "avions vu",
          "vous": "aviez vu",
          "ils/elles": "avaient vu"
        },
        "passé antérieur": {
          "j'": "eus vu",
          "tu": "eus vu",
          "il/elle": "eut vu",
          "nous": "eûmes vu",
          "vous": "eûtes vu",
          "ils/elles": "eurent vu"
        },
        "futur antérieur": {
          "j'": "aurai vu",
          "tu": "auras vu",
          "il/elle": "aura vu",
          "nous": "aurons vu",
          "vous": "aurez vu",
          "ils/elles": "auront vu"
        },
        "conditionnel passé première forme": {
          "j'": "aurais vu",
          "tu": "aurais vu",
          "il/elle": "aurait vu",
          "nous": "aurions vu",
          "vous": "auriez vu",
          "ils/elles": "auraient vu"
        }
      }
    },
    {
      "infinitive": "vouloir",
      "conjugations": {
        "présent": {
          "je": "veux",
          "tu": "veux",
          "il/elle": "veut",
          "nous": "voulons",
          "vous": "voulez",
          "ils/elles": "veulent"
        },
        "passé composé": {
          "je": "ai voulu",
          "tu": "as voulu",
          "il/elle": "a voulu",
          "nous": "avons voulu",
          "vous": "avez voulu",
          "ils/elles": "ont voulu"
        },
        "imparfait": {
          "je": "voulais",
          "tu": "voulais",
          "il/elle": "voulait",
          "nous": "voulions",
          "vous": "vouliez",
          "ils/elles": "voulaient"
        },
        "passé simple": {
          "je": "voulus",
          "tu": "voulus",
          "il/elle": "voulut",
          "nous": "voulûmes",
          "vous": "voulûtes",
          "ils/elles": "voulurent"
        },
        "futur simple": {
          "je": "voudrai",
          "tu": "voudras",
          "il/elle": "voudra",
          "nous": "voudrons",
          "vous": "voudrez",
          "ils/elles": "voudront"
        },
        "imparfait du subjonctif": {
          "que je": "voulusse",
          "que tu": "voulusses",
          "qu’il/elle": "voulût",
          "que nous": "voulussions",
          "que vous": "voulussiez",
          "qu’ils/elles": "voulussent"
        },
        "subjonctif passé": {
          "que j'": "aie voulu",
          "que tu": "aies voulu",
          "qu’il/elle": "ait voulu",
          "que nous": "ayons voulu",
          "que vous": "ayez voulu",
          "qu’ils/elles": "aient voulu"
        },
        "conditionnel présent": {
          "je": "voudrais",
          "tu": "voudrais",
          "il/elle": "voudrait",
          "nous": "voudrions",
          "vous": "voudriez",
          "ils/elles": "voudraient"
        },
        "plus-que-parfait": {
          "j'": "avais voulu",
          "tu": "avais voulu",
          "il/elle": "avait voulu",
          "nous": "avions voulu",
          "vous": "aviez voulu",
          "ils/elles": "avaient voulu"
        },
        "passé antérieur": {
          "j'": "eus voulu",
          "tu": "eus voulu",
          "il/elle": "eut voulu",
          "nous": "eûmes voulu",
          "vous": "eûtes voulu",
          "ils/elles": "eurent voulu"
        },
        "futur antérieur": {
          "j'": "aurai voulu",
          "tu": "auras voulu",
          "il/elle": "aura voulu",
          "nous": "aurons voulu",
          "vous": "aurez voulu",
          "ils/elles": "auront voulu"
        },
        "conditionnel passé première forme": {
          "j'": "aurais voulu",
          "tu": "aurais voulu",
          "il/elle": "aurait voulu",
          "nous": "aurions voulu",
          "vous": "auriez voulu",
          "ils/elles": "auraient voulu"
        }
      }
    },
    {
      "infinitive": "venir",
      "conjugations": {
        "présent": {
          "je": "viens",
          "tu": "viens",
          "il/elle": "vient",
          "nous": "venons",
          "vous": "venez",
          "ils/elles": "viennent"
        },
        "passé composé": {
          "je": "suis venu",
          "tu": "es venu",
          "il": "est venu",
          "nous": "sommes venus",
          "vous": "êtes venus",
          "ils": "sont venus"
        },
        "imparfait": {
          "je": "venais",
          "tu": "venais",
          "il/elle": "venait",
          "nous": "venions",
          "vous": "veniez",
          "ils/elles": "venaient"
        },
        "passé simple": {
          "je": "vins",
          "tu": "vins",
          "il/elle": "vint",
          "nous": "vînmes",
          "vous": "vîntes",
          "ils/elles": "vinrent"
        },
        "futur simple": {
          "je": "viendrai",
          "tu": "viendras",
          "il/elle": "viendra",
          "nous": "viendrons",
          "vous": "viendrez",
          "ils/elles": "viendront"
        },
        "imparfait du subjonctif": {
          "que je": "vinsse",
          "que tu": "vinsses",
          "qu’il/elle": "vînt",
          "que nous": "vinssions",
          "que vous": "vinssiez",
          "qu’ils/elles": "vinssent"
        },
        "subjonctif passé": {
          "que je": "aie venu",
          "que tu": "aies venu",
          "qu’il": "ait venu",
          "que nous": "ayons venu",
          "que vous": "ayez venu",
          "qu’ils/elles": "aient venu"
        },
        "conditionnel présent": {
          "je": "viendrais",
          "tu": "viendrais",
          "il/elle": "viendrait",
          "nous": "viendrions",
          "vous": "viendriez",
          "ils/elles": "viendraient"
        },
        "plus-que-parfait": {
          "j'": "étais venu",
          "tu": "étais venu",
          "il": "était venu",
          "nous": "étions venus",
          "vous": "étiez venus",
          "ils": "étaient venus"
        },
        "passé antérieur": {
          "je": "fus venu",
          "tu": "fus venu",
          "il/elle": "fut venu",
          "nous": "fûmes venus",
          "vous": "fûtes venus",
          "ils/elles": "furent venus"
        },
        "futur antérieur": {
          "je": "serai venu",
          "tu": "seras venu",
          "il": "sera venu",
          "nous": "serons venus",
          "vous": "serez venus",
          "ils/elles": "seront venus"
        },
        "conditionnel passé première forme": {
          "je": "serais venu",
          "tu": "serais venu",
          "il/elle": "serait venu",
          "nous": "serions venus",
          "vous": "seriez venus",
          "ils/elles": "seraient venus"
        }
      }
    },
    {
      "infinitive": "devoir",
      "conjugations": {
        "présent": {
          "je": "dois",
          "tu": "dois",
          "il/elle": "doit",
          "nous": "devons",
          "vous": "devez",
          "ils/elles": "doivent"
        },
        "passé composé": {
          "je": "ai dû",
          "tu": "as dû",
          "il/elle": "a dû",
          "nous": "avons dû",
          "vous": "avez dû",
          "ils/elles": "ont dû"
        },
        "imparfait": {
          "je": "devais",
          "tu": "devais",
          "il/elle": "devait",
          "nous": "devions",
          "vous": "deviez",
          "ils/elles": "devaient"
        },
        "passé simple": {
          "je": "dus",
          "tu": "dus",
          "il/elle": "dut",
          "nous": "dûmes",
          "vous": "dûtes",
          "ils/elles": "durent"
        },
        "futur simple": {
          "je": "devrai",
          "tu": "devras",
          "il/elle": "devra",
          "nous": "devrons",
          "vous": "devrez",
          "ils/elles": "devront"
        },
        "imparfait du subjonctif": {
          "que je": "devisse",
          "que tu": "devisses",
          "qu’il/elle": "devît",
          "que nous": "devissions",
          "que vous": "devissiez",
          "qu’ils/elles": "devissent"
        },
        "subjonctif passé": {
          "que je": "aie dû",
          "que tu": "aies dû",
          "qu’il/elle": "ait dû",
          "que nous": "ayons dû",
          "que vous": "ayez dû",
          "qu’ils/elles": "aient dû"
        },
        "conditionnel présent": {
          "je": "devrais",
          "tu": "devrais",
          "il/elle": "devrait",
          "nous": "devrions",
          "vous": "devriez",
          "ils/elles": "devraient"
        },
        "plus-que-parfait": {
          "je": "avais dû",
          "tu": "avais dû",
          "il/elle": "avait dû",
          "nous": "avions dû",
          "vous": "aviez dû",
          "ils/elles": "avaient dû"
        },
        "passé antérieur": {
          "je": "eus dû",
          "tu": "eus dû",
          "il/elle": "eut dû",
          "nous": "eûmes dû",
          "vous": "eûtes dû",
          "ils/elles": "eurent dû"
        },
        "futur antérieur": {
          "je": "aurai dû",
          "tu": "auras dû",
          "il/elle": "aura dû",
          "nous": "aurons dû",
          "vous": "aurez dû",
          "ils/elles": "auront dû"
        },
        "conditionnel passé première forme": {
          "je": "aurais dû",
          "tu": "aurais dû",
          "il/elle": "aurait dû",
          "nous": "aurions dû",
          "vous": "auriez dû",
          "ils/elles": "auraient dû"
        }
      }
    },
    {
      "infinitive": "prendre",
      "conjugations": {
        "présent": {
          "je": "prends",
          "tu": "prends",
          "il/elle": "prend",
          "nous": "prenons",
          "vous": "prenez",
          "ils/elles": "prennent"
        },
        "passé composé": {
          "je": "ai pris",
          "tu": "as pris",
          "il/elle": "a pris",
          "nous": "avons pris",
          "vous": "avez pris",
          "ils/elles": "ont pris"
        },
        "imparfait": {
          "je": "prenais",
          "tu": "prenais",
          "il/elle": "prenait",
          "nous": "prenions",
          "vous": "preniez",
          "ils/elles": "prenaient"
        },
        "passé simple": {
          "je": "pris",
          "tu": "pris",
          "il/elle": "prit",
          "nous": "prîmes",
          "vous": "prîtes",
          "ils/elles": "prirent"
        },
        "futur simple": {
          "je": "prendrai",
          "tu": "prendras",
          "il/elle": "prendra",
          "nous": "prendrons",
          "vous": "prendrez",
          "ils/elles": "prendront"
        },
        "imparfait du subjonctif": {
          "que je": "prisse",
          "que tu": "prisses",
          "qu’il/elle": "prît",
          "que nous": "prissions",
          "que vous": "prissiez",
          "qu’ils/elles": "prissent"
        },
        "subjonctif passé": {
          "que je": "aie pris",
          "que tu": "aies pris",
          "qu’il/elle": "ait pris",
          "que nous": "ayons pris",
          "que vous": "ayez pris",
          "qu’ils/elles": "aient pris"
        },
        "conditionnel présent": {
          "je": "prendrais",
          "tu": "prendrais",
          "il/elle": "prendrait",
          "nous": "prendrions",
          "vous": "prendriez",
          "ils/elles": "prendraient"
        },
        "plus-que-parfait": {
          "je": "avais pris",
          "tu": "avais pris",
          "il/elle": "avait pris",
          "nous": "avions pris",
          "vous": "aviez pris",
          "ils/elles": "avaient pris"
        },
        "passé antérieur": {
          "je": "eus pris",
          "tu": "eus pris",
          "il/elle": "eut pris",
          "nous": "eûmes pris",
          "vous": "eûtes pris",
          "ils/elles": "eurent pris"
        },
        "futur antérieur": {
          "je": "aurai pris",
          "tu": "auras pris",
          "il/elle": "aura pris",
          "nous": "aurons pris",
          "vous": "aurez pris",
          "ils/elles": "auront pris"
        },
        "conditionnel passé première forme": {
          "je": "aurais pris",
          "tu": "aurais pris",
          "il/elle": "aurait pris",
          "nous": "aurions pris",
          "vous": "auriez pris",
          "ils/elles": "auraient pris"
        }
      }
    },
	{
      "infinitive": "trouver",
      "conjugations": {
        "présent": {
          "je": "trouve",
          "tu": "trouves",
          "il/elle": "trouve",
          "nous": "trouvons",
          "vous": "trouvez",
          "ils/elles": "trouvent"
        },
        "passé composé": {
          "je": "ai trouvé",
          "tu": "as trouvé",
          "il/elle": "a trouvé",
          "nous": "avons trouvé",
          "vous": "avez trouvé",
          "ils/elles": "ont trouvé"
        },
        "imparfait": {
          "je": "trouvais",
          "tu": "trouvais",
          "il/elle": "trouvait",
          "nous": "trouvions",
          "vous": "trouviez",
          "ils/elles": "trouvaient"
        },
        "passé simple": {
          "je": "trouvai",
          "tu": "trouvas",
          "il/elle": "trouva",
          "nous": "trouvâmes",
          "vous": "trouvâtes",
          "ils/elles": "trouvèrent"
        },
        "futur simple": {
          "je": "trouverai",
          "tu": "trouveras",
          "il/elle": "trouvera",
          "nous": "trouverons",
          "vous": "trouverez",
          "ils/elles": "trouveront"
        },
        "imparfait du subjonctif": {
          "que je": "trouvasse",
          "que tu": "trouvasses",
          "qu’il/elle": "trouvât",
          "que nous": "trouvassions",
          "que vous": "trouvassiez",
          "qu’ils/elles": "trouvassent"
        },
        "subjonctif passé": {
          "que je": "aie trouvé",
          "que tu": "aies trouvé",
          "qu’il/elle": "ait trouvé",
          "que nous": "ayons trouvé",
          "que vous": "ayez trouvé",
          "qu’ils/elles": "aient trouvé"
        },
        "conditionnel présent": {
          "je": "trouverais",
          "tu": "trouverais",
          "il/elle": "trouverait",
          "nous": "trouverions",
          "vous": "trouveriez",
          "ils/elles": "trouveraient"
        },
        "plus-que-parfait": {
          "je": "avais trouvé",
          "tu": "avais trouvé",
          "il/elle": "avait trouvé",
          "nous": "avions trouvé",
          "vous": "aviez trouvé",
          "ils/elles": "avaient trouvé"
        },
        "passé antérieur": {
          "je": "eus trouvé",
          "tu": "eus trouvé",
          "il/elle": "eut trouvé",
          "nous": "eûmes trouvé",
          "vous": "eûtes trouvé",
          "ils/elles": "eurent trouvé"
        },
        "futur antérieur": {
          "je": "aurai trouvé",
          "tu": "auras trouvé",
          "il/elle": "aura trouvé",
          "nous": "aurons trouvé",
          "vous": "aurez trouvé",
          "ils/elles": "auront trouvé"
        },
        "conditionnel passé première forme": {
          "je": "aurais trouvé",
          "tu": "aurais trouvé",
          "il/elle": "aurait trouvé",
          "nous": "aurions trouvé",
          "vous": "auriez trouvé",
          "ils/elles": "auraient trouvé"
        }
      }
    },
    {
      "infinitive": "donner",
      "conjugations": {
        "présent": {
          "je": "donne",
          "tu": "donnes",
          "il/elle": "donne",
          "nous": "donnons",
          "vous": "donnez",
          "ils/elles": "donnent"
        },
        "passé composé": {
          "je": "ai donné",
          "tu": "as donné",
          "il/elle": "a donné",
          "nous": "avons donné",
          "vous": "avez donné",
          "ils/elles": "ont donné"
        },
        "imparfait": {
          "je": "donnais",
          "tu": "donnais",
          "il/elle": "donnait",
          "nous": "donnions",
          "vous": "donniez",
          "ils/elles": "donnaient"
        },
        "passé simple": {
          "je": "donnai",
          "tu": "donnas",
          "il/elle": "donna",
          "nous": "donnâmes",
          "vous": "donnâtes",
          "ils/elles": "donnèrent"
        },
        "futur simple": {
          "je": "donnerai",
          "tu": "donneras",
          "il/elle": "donnera",
          "nous": "donnerons",
          "vous": "donnerez",
          "ils/elles": "donneront"
        },
        "imparfait du subjonctif": {
          "que je": "donnasse",
          "que tu": "donnasses",
          "qu’il/elle": "donnât",
          "que nous": "donnassions",
          "que vous": "donnassiez",
          "qu’ils/elles": "donnassent"
        },
        "subjonctif passé": {
          "que je": "aie donné",
          "que tu": "aies donné",
          "qu’il/elle": "ait donné",
          "que nous": "ayons donné",
          "que vous": "ayez donné",
          "qu’ils/elles": "aient donné"
        },
        "conditionnel présent": {
          "je": "donnerais",
          "tu": "donnerais",
          "il/elle": "donnerait",
          "nous": "donnerions",
          "vous": "donneriez",
          "ils/elles": "donneraient"
        },
        "plus-que-parfait": {
          "je": "avais donné",
          "tu": "avais donné",
          "il/elle": "avait donné",
          "nous": "avions donné",
          "vous": "aviez donné",
          "ils/elles": "avaient donné"
        },
        "passé antérieur": {
          "je": "eus donné",
          "tu": "eus donné",
          "il/elle": "eut donné",
          "nous": "eûmes donné",
          "vous": "eûtes donné",
          "ils/elles": "eurent donné"
        },
        "futur antérieur": {
          "je": "aurai donné",
          "tu": "auras donné",
          "il/elle": "aura donné",
          "nous": "aurons donné",
          "vous": "aurez donné",
          "ils/elles": "auront donné"
        },
        "conditionnel passé première forme": {
          "je": "aurais donné",
          "tu": "aurais donné",
          "il/elle": "aurait donné",
          "nous": "aurions donné",
          "vous": "auriez donné",
          "ils/elles": "auraient donné"
        }
      }
    },
    {
      "infinitive": "parler",
      "conjugations": {
        "présent": {
          "je": "parle",
          "tu": "parles",
          "il/elle": "parle",
          "nous": "parlons",
          "vous": "parlez",
          "ils/elles": "parlent"
        },
        "passé composé": {
          "je": "ai parlé",
          "tu": "as parlé",
          "il/elle": "a parlé",
          "nous": "avons parlé",
          "vous": "avez parlé",
          "ils/elles": "ont parlé"
        },
        "imparfait": {
          "je": "parlais",
          "tu": "parlais",
          "il/elle": "parlait",
          "nous": "parlions",
          "vous": "parliez",
          "ils/elles": "parlaient"
        },
        "passé simple": {
          "je": "parlai",
          "tu": "parlas",
          "il/elle": "parla",
          "nous": "parlâmes",
          "vous": "parlâtes",
          "ils/elles": "parlèrent"
        },
        "futur simple": {
          "je": "parlerai",
          "tu": "parleras",
          "il/elle": "parlera",
          "nous": "parlerons",
          "vous": "parlerez",
          "ils/elles": "parleront"
        },
        "imparfait du subjonctif": {
          "que je": "parlasse",
          "que tu": "parlasses",
          "qu’il/elle": "parlât",
          "que nous": "parlassions",
          "que vous": "parlassiez",
          "qu’ils/elles": "parlassent"
        },
        "subjonctif passé": {
          "que je": "aie parlé",
          "que tu": "aies parlé",
          "qu’il/elle": "ait parlé",
          "que nous": "ayons parlé",
          "que vous": "ayez parlé",
          "qu’ils/elles": "aient parlé"
        },
        "conditionnel présent": {
          "je": "parlerais",
          "tu": "parlerais",
          "il/elle": "parlerait",
          "nous": "parlerions",
          "vous": "parleriez",
          "ils/elles": "parleraient"
        },
        "plus-que-parfait": {
          "je": "avais parlé",
          "tu": "avais parlé",
          "il/elle": "avait parlé",
          "nous": "avions parlé",
          "vous": "aviez parlé",
          "ils/elles": "avaient parlé"
        },
        "passé antérieur": {
          "je": "eus parlé",
          "tu": "eus parlé",
          "il/elle": "eut parlé",
          "nous": "eûmes parlé",
          "vous": "eûtes parlé",
          "ils/elles": "eurent parlé"
        },
        "futur antérieur": {
          "je": "aurai parlé",
          "tu": "auras parlé",
          "il/elle": "aura parlé",
          "nous": "aurons parlé",
          "vous": "aurez parlé",
          "ils/elles": "auront parlé"
        },
        "conditionnel passé première forme": {
          "je": "aurais parlé",
          "tu": "aurais parlé",
          "il/elle": "aurait parlé",
          "nous": "aurions parlé",
          "vous": "auriez parlé",
          "ils/elles": "auraient parlé"
        }
      }
    },
    {
      "infinitive": "aimer",
      "conjugations": {
        "présent": {
          "je": "aime",
          "tu": "aimes",
          "il/elle": "aime",
          "nous": "aimons",
          "vous": "aimez",
          "ils/elles": "aiment"
        },
        "passé composé": {
          "je": "ai aimé",
          "tu": "as aimé",
          "il/elle": "a aimé",
          "nous": "avons aimé",
          "vous": "avez aimé",
          "ils/elles": "ont aimé"
        },
        "imparfait": {
          "je": "aimais",
          "tu": "aimais",
          "il/elle": "aimait",
          "nous": "aimions",
          "vous": "aimiez",
          "ils/elles": "aimaient"
        },
        "passé simple": {
          "je": "aimai",
          "tu": "aimas",
          "il/elle": "aima",
          "nous": "aimâmes",
          "vous": "aimâtes",
          "ils/elles": "aimèrent"
        },
        "futur simple": {
          "je": "aimerai",
          "tu": "aimeras",
          "il/elle": "aimera",
          "nous": "aimerons",
          "vous": "aimerez",
          "ils/elles": "aimeront"
        },
        "imparfait du subjonctif": {
          "que je": "aimasse",
          "que tu": "aimasses",
          "qu’il/elle": "aimât",
          "que nous": "aimassions",
          "que vous": "aimassiez",
          "qu’ils/elles": "aimassent"
        },
        "subjonctif passé": {
          "que je": "aie aimé",
          "que tu": "aies aimé",
          "qu’il/elle": "ait aimé",
          "que nous": "ayons aimé",
          "que vous": "ayez aimé",
          "qu’ils/elles": "aient aimé"
        },
        "conditionnel présent": {
          "je": "aimerais",
          "tu": "aimerais",
          "il/elle": "aimerait",
          "nous": "aimerions",
          "vous": "aimeriez",
          "ils/elles": "aimeraient"
        },
        "plus-que-parfait": {
          "je": "avais aimé",
          "tu": "avais aimé",
          "il/elle": "avait aimé",
          "nous": "avions aimé",
          "vous": "aviez aimé",
          "ils/elles": "avaient aimé"
        },
        "passé antérieur": {
          "je": "eus aimé",
          "tu": "eus aimé",
          "il/elle": "eut aimé",
          "nous": "eûmes aimé",
          "vous": "eûtes aimé",
          "ils/elles": "eurent aimé"
        },
        "futur antérieur": {
          "je": "aurai aimé",
          "tu": "auras aimé",
          "il/elle": "aura aimé",
          "nous": "aurons aimé",
          "vous": "aurez aimé",
          "ils/elles": "auront aimé"
        },
        "conditionnel passé première forme": {
          "je": "aurais aimé",
          "tu": "aurais aimé",
          "il/elle": "aurait aimé",
          "nous": "aurions aimé",
          "vous": "auriez aimé",
          "ils/elles": "auraient aimé"
        }
      }
    },
	{
      "infinitive": "coudre",
      "conjugations": {
        "présent": {
          "je": "couds",
          "tu": "couds",
          "il/elle": "coud",
          "nous": "cousons",
          "vous": "cousez",
          "ils/elles": "cousent"
        },
        "passé composé": {
          "j'": "ai cousu",
          "tu": "as cousu",
          "il/elle": "a cousu",
          "nous": "avons cousu",
          "vous": "avez cousu",
          "ils/elles": "ont cousu"
        },
        "imparfait": {
          "je": "cousais",
          "tu": "cousais",
          "il/elle": "cousait",
          "nous": "cousions",
          "vous": "cousiez",
          "ils/elles": "cousaient"
        },
        "passé simple": {
          "je": "cousis",
          "tu": "cousis",
          "il/elle": "cousit",
          "nous": "cousîmes",
          "vous": "cousîtes",
          "ils/elles": "cousirent"
        },
        "futur simple": {
          "je": "coudrai",
          "tu": "coudras",
          "il/elle": "coudra",
          "nous": "coudrons",
          "vous": "coudrez",
          "ils/elles": "coudront"
        },
        "imparfait du subjonctif": {
          "que je": "cousisse",
          "que tu": "cousisses",
          "qu'il/elle": "cousît",
          "que nous": "cousissions",
          "que vous": "cousissiez",
          "qu'ils/elles": "cousissent"
        },
        "subjonctif passé": {
          "que j'": "aie cousu",
          "que tu": "aies cousu",
          "qu'il/elle": "ait cousu",
          "que nous": "ayons cousu",
          "que vous": "ayez cousu",
          "qu'ils/elles": "aient cousu"
        },
        "conditionnel présent": {
          "je": "coudrais",
          "tu": "coudrais",
          "il/elle": "coudrait",
          "nous": "coudrions",
          "vous": "coudriez",
          "ils/elles": "coudraient"
        },
        "plus-que-parfait": {
          "j'": "avais cousu",
          "tu": "avais cousu",
          "il/elle": "avait cousu",
          "nous": "avions cousu",
          "vous": "aviez cousu",
          "ils/elles": "avaient cousu"
        },
        "passé antérieur": {
          "j'": "eus cousu",
          "tu": "eus cousu",
          "il/elle": "eut cousu",
          "nous": "eûmes cousu",
          "vous": "eûtes cousu",
          "ils/elles": "eurent cousu"
        },
        "futur antérieur": {
          "je": "aurai cousu",
          "tu": "auras cousu",
          "il/elle": "aura cousu",
          "nous": "aurons cousu",
          "vous": "aurez cousu",
          "ils/elles": "auront cousu"
        },
        "conditionnel passé première forme": {
          "je": "aurais cousu",
          "tu": "aurais cousu",
          "il/elle": "aurait cousu",
          "nous": "aurions cousu",
          "vous": "auriez cousu",
          "ils/elles": "auraient cousu"
        }
      }
    },
	{
      "infinitive": "circonscrire",
      "conjugations": {
        "présent": {
          "je": "circonscris",
          "tu": "circonscris",
          "il/elle": "circonscrit",
          "nous": "circonscissons",
          "vous": "circonscissez",
          "ils/elles": "circonscrivent"
        },
        "passé composé": {
          "j'": "ai circonscrit",
          "tu": "as circonscrit",
          "il/elle": "a circonscrit",
          "nous": "avons circonscrit",
          "vous": "avez circonscrit",
          "ils/elles": "ont circonscrit"
        },
        "imparfait": {
          "je": "circonscrivais",
          "tu": "circonscrivais",
          "il/elle": "circonscrivait",
          "nous": "circonscrivions",
          "vous": "circonscriviez",
          "ils/elles": "circonscrivaient"
        },
        "passé simple": {
          "je": "circonscrivis",
          "tu": "circonscrivis",
          "il/elle": "circonscrivit",
          "nous": "circonscrivîmes",
          "vous": "circonscrivîtes",
          "ils/elles": "circonscrivirent"
        },
        "futur simple": {
          "je": "circonscrirai",
          "tu": "circonscriras",
          "il/elle": "circonscrira",
          "nous": "circonscrirons",
          "vous": "circonscrirez",
          "ils/elles": "circonscriront"
        },
        "imparfait du subjonctif": {
          "que je": "circonscrivisse",
          "que tu": "circonscrivisses",
          "qu'il/elle": "circonscrivît",
          "que nous": "circonscrivissions",
          "que vous": "circonscrivissiez",
          "qu'ils/elles": "circonscrivissent"
        },
        "subjonctif passé": {
          "que j'": "aie circonscrit",
          "que tu": "aies circonscrit",
          "qu'il/elle": "ait circonscrit",
          "que nous": "ayons circonscrit",
          "que vous": "ayez circonscrit",
          "qu'ils/elles": "aient circonscrit"
        },
        "conditionnel présent": {
          "je": "circonscrirais",
          "tu": "circonscrirais",
          "il/elle": "circonscrirait",
          "nous": "circonscririons",
          "vous": "circonscririez",
          "ils/elles": "circonscriraient"
        },
        "plus-que-parfait": {
          "j'": "avais circonscrit",
          "tu": "avais circonscrit",
          "il/elle": "avait circonscrit",
          "nous": "avions circonscrit",
          "vous": "aviez circonscrit",
          "ils/elles": "avaient circonscrit"
        },
        "passé antérieur": {
          "j'": "eus circonscrit",
          "tu": "eus circonscrit",
          "il/elle": "eut circonscrit",
          "nous": "eûmes circonscrit",
          "vous": "eûtes circonscrit",
          "ils/elles": "eurent circonscrit"
        },
        "futur antérieur": {
          "j'": "aurai circonscrit",
          "tu": "auras circonscrit",
          "il/elle": "aura circonscrit",
          "nous": "aurons circonscrit",
          "vous": "aurez circonscrit",
          "ils/elles": "auront circonscrit"
        },
        "conditionnel passé première forme": {
          "j'": "aurais circonscrit",
          "tu": "aurais circonscrit",
          "il/elle": "aurait circonscrit",
          "nous": "aurions circonscrit",
          "vous": "auriez circonscrit",
          "ils/elles": "auraient circonscrit"
        }
      }
    },
	{
      "infinitive": "bouillir",
      "conjugations": {
        "présent": {
          "je": "boue",
          "tu": "bous",
          "il/elle": "bout",
          "nous": "bouillons",
          "vous": "bouillez",
          "ils/elles": "bouillent"
        },
        "passé composé": {
          "j'": "ai bouilli",
          "tu": "as bouilli",
          "il/elle": "a bouilli",
          "nous": "avons bouilli",
          "vous": "avez bouilli",
          "ils/elles": "ont bouilli"
        },
        "imparfait": {
          "je": "bouillais",
          "tu": "bouillais",
          "il/elle": "bouillait",
          "nous": "bouillions",
          "vous": "bouilliez",
          "ils/elles": "bouillaient"
        },
        "passé simple": {
          "je": "bouillis",
          "tu": "bouillis",
          "il/elle": "bouillit",
          "nous": "bouillîmes",
          "vous": "bouillîtes",
          "ils/elles": "bouillirent"
        },
        "futur simple": {
          "je": "bouillirai",
          "tu": "bouilliras",
          "il/elle": "bouillira",
          "nous": "bouillirons",
          "vous": "bouillirez",
          "ils/elles": "bouilliront"
        },
        "imparfait du subjonctif": {
          "que je": "bouillisse",
          "que tu": "bouillisses",
          "qu'il/elle": "bouillît",
          "que nous": "bouillissions",
          "que vous": "bouillissiez",
          "qu'ils/elles": "bouillissent"
        },
        "subjonctif passé": {
          "que j'": "aie bouilli",
          "que tu": "aies bouilli",
          "qu'il/elle": "ait bouilli",
          "que nous": "ayons bouilli",
          "que vous": "ayez bouilli",
          "qu'ils/elles": "aient bouilli"
        },
        "conditionnel présent": {
          "je": "bouillirais",
          "tu": "bouillirais",
          "il/elle": "bouillirait",
          "nous": "bouillirions",
          "vous": "bouilliriez",
          "ils/elles": "bouilliraient"
        },
        "plus-que-parfait": {
          "j'": "avais bouilli",
          "tu": "avais bouilli",
          "il/elle": "avait bouilli",
          "nous": "avions bouilli",
          "vous": "aviez bouilli",
          "ils/elles": "avaient bouilli"
        },
        "passé antérieur": {
          "j'": "eus bouilli",
          "tu": "eus bouilli",
          "il/elle": "eut bouilli",
          "nous": "eûmes bouilli",
          "vous": "eûtes bouilli",
          "ils/elles": "eurent bouilli"
        },
        "futur antérieur": {
          "j'": "aurai bouilli",
          "tu": "auras bouilli",
          "il/elle": "aura bouilli",
          "nous": "aurons bouilli",
          "vous": "aurez bouilli",
          "ils/elles": "auront bouilli"
        },
        "conditionnel passé première forme": {
          "j'": "aurais bouilli",
          "tu": "aurais bouilli",
          "il/elle": "aurait bouilli",
          "nous": "aurions bouilli",
          "vous": "auriez bouilli",
          "ils/elles": "auraient bouilli"
        }
      }
    },
	{
      "infinitive": "atteindre",
      "conjugations": {
        "présent": {
          "je": "atteins",
          "tu": "atteins",
          "il/elle": "atteint",
          "nous": "atteignons",
          "vous": "atteignez",
          "ils/elles": "atteignent"
        },
        "passé composé": {
          "j'": "ai atteint",
          "tu": "as atteint",
          "il/elle": "a atteint",
          "nous": "avons atteint",
          "vous": "avez atteint",
          "ils/elles": "ont atteint"
        },
        "imparfait": {
          "je": "atteignais",
          "tu": "atteignais",
          "il/elle": "atteignait",
          "nous": "atteignions",
          "vous": "atteigniez",
          "ils/elles": "atteignaient"
        },
        "passé simple": {
          "je": "atteignis",
          "tu": "atteignis",
          "il/elle": "atteignit",
          "nous": "atteignîmes",
          "vous": "atteignîtes",
          "ils/elles": "atteignirent"
        },
        "futur simple": {
          "je": "atteindrai",
          "tu": "atteindras",
          "il/elle": "atteindra",
          "nous": "atteindrons",
          "vous": "atteindrez",
          "ils/elles": "atteindront"
        },
        "imparfait du subjonctif": {
          "que je": "atteignisse",
          "que tu": "atteignisses",
          "qu'il/elle": "atteignît",
          "que nous": "atteignissions",
          "que vous": "atteignissiez",
          "qu'ils/elles": "atteignissent"
        },
        "subjonctif passé": {
          "que je": "aie atteint",
          "que tu": "aies atteint",
          "qu'il/elle": "ait atteint",
          "que nous": "ayons atteint",
          "que vous": "ayez atteint",
          "qu'ils/elles": "aient atteint"
        },
        "conditionnel présent": {
          "je": "atteindrais",
          "tu": "atteindrais",
          "il/elle": "atteindrait",
          "nous": "atteindrions",
          "vous": "atteindriez",
          "ils/elles": "atteindraient"
        },
        "plus-que-parfait": {
          "j'": "avais atteint",
          "tu": "avais atteint",
          "il/elle": "avait atteint",
          "nous": "avions atteint",
          "vous": "aviez atteint",
          "ils/elles": "avaient atteint"
        },
        "passé antérieur": {
          "j'": "eus atteint",
          "tu": "eus atteint",
          "il/elle": "eut atteint",
          "nous": "eûmes atteint",
          "vous": "eûtes atteint",
          "ils/elles": "eurent atteint"
        },
        "futur antérieur": {
          "je": "aurai atteint",
          "tu": "auras atteint",
          "il/elle": "aura atteint",
          "nous": "aurons atteint",
          "vous": "aurez atteint",
          "ils/elles": "auront atteint"
        },
        "conditionnel passé première forme": {
          "je": "aurais atteint",
          "tu": "aurais atteint",
          "il/elle": "aurait atteint",
          "nous": "aurions atteint",
          "vous": "auriez atteint",
          "ils/elles": "auraient atteint"
        }
      }
    },
	{
      "infinitive": "chercher",
      "conjugations": {
        "présent": {
          "je": "cherche",
          "tu": "cherches",
          "il/elle": "cherche",
          "nous": "cherchons",
          "vous": "cherchez",
          "ils/elles": "cherchent"
        },
        "passé composé": {
          "j'": "ai cherché",
          "tu": "as cherché",
          "il/elle": "a cherché",
          "nous": "avons cherché",
          "vous": "avez cherché",
          "ils/elles": "ont cherché"
        },
        "imparfait": {
          "je": "cherchais",
          "tu": "cherchais",
          "il/elle": "cherchait",
          "nous": "cherchions",
          "vous": "cherchiez",
          "ils/elles": "cherchaient"
        },
        "passé simple": {
          "je": "cherchai",
          "tu": "cherchas",
          "il/elle": "chercha",
          "nous": "cherchâmes",
          "vous": "cherchâtes",
          "ils/elles": "cherchèrent"
        },
        "futur simple": {
          "je": "chercherai",
          "tu": "chercheras",
          "il/elle": "cherchera",
          "nous": "chercherons",
          "vous": "chercherez",
          "ils/elles": "chercheront"
        },
        "imparfait du subjonctif": {
          "que je": "cherchasse",
          "que tu": "cherchasses",
          "qu'il/elle": "cherchât",
          "que nous": "cherchassions",
          "que vous": "cherchassiez",
          "qu'ils/elles": "cherchassent"
        },
        "subjonctif passé": {
          "que je": "aie cherché",
          "que tu": "aies cherché",
          "qu'il/elle": "ait cherché",
          "que nous": "ayons cherché",
          "que vous": "ayez cherché",
          "qu'ils/elles": "aient cherché"
        },
        "conditionnel présent": {
          "je": "chercherais",
          "tu": "chercherais",
          "il/elle": "chercherait",
          "nous": "chercherions",
          "vous": "chercheriez",
          "ils/elles": "chercheraient"
        },
        "plus-que-parfait": {
          "j'": "avais cherché",
          "tu": "avais cherché",
          "il/elle": "avait cherché",
          "nous": "avions cherché",
          "vous": "aviez cherché",
          "ils/elles": "avaient cherché"
        },
        "passé antérieur": {
          "j'": "eus cherché",
          "tu": "eus cherché",
          "il/elle": "eut cherché",
          "nous": "eûmes cherché",
          "vous": "eûtes cherché",
          "ils/elles": "eurent cherché"
        },
        "futur antérieur": {
          "je": "aurai cherché",
          "tu": "auras cherché",
          "il/elle": "aura cherché",
          "nous": "aurons cherché",
          "vous": "aurez cherché",
          "ils/elles": "auront cherché"
        },
        "conditionnel passé première forme": {
          "je": "aurais cherché",
          "tu": "aurais cherché",
          "il/elle": "aurait cherché",
          "nous": "aurions cherché",
          "vous": "auriez cherché",
          "ils/elles": "auraient cherché"
        }
      }
    },
    {
      "infinitive": "cueillir",
      "conjugations": {
        "présent": {
          "je": "cueille",
          "tu": "cueilles",
          "il/elle": "cueille",
          "nous": "cueillons",
          "vous": "cueillez",
          "ils/elles": "cueillent"
        },
        "passé composé": {
          "j'": "ai cueilli",
          "tu": "as cueilli",
          "il/elle": "a cueilli",
          "nous": "avons cueilli",
          "vous": "avez cueilli",
          "ils/elles": "ont cueilli"
        },
        "imparfait": {
          "je": "cueillais",
          "tu": "cueillais",
          "il/elle": "cueillait",
          "nous": "cueillions",
          "vous": "cueilliez",
          "ils/elles": "cueillaient"
        },
        "passé simple": {
          "je": "cueillis",
          "tu": "cueillis",
          "il/elle": "cueillit",
          "nous": "cueillîmes",
          "vous": "cueillîtes",
          "ils/elles": "cueillirent"
        },
        "futur simple": {
          "je": "cueillerai",
          "tu": "cueilleras",
          "il/elle": "cueillera",
          "nous": "cueillerons",
          "vous": "cueillerez",
          "ils/elles": "cueilleront"
        },
        "imparfait du subjonctif": {
          "que je": "cueillisse",
          "que tu": "cueillisses",
          "qu'il/elle": "cueillît",
          "que nous": "cueillissions",
          "que vous": "cueillissiez",
          "qu'ils/elles": "cueillissent"
        },
        "subjonctif passé": {
          "que je": "aie cueilli",
          "que tu": "aies cueilli",
          "qu'il/elle": "ait cueilli",
          "que nous": "ayons cueilli",
          "que vous": "ayez cueilli",
          "qu'ils/elles": "aient cueilli"
        },
        "conditionnel présent": {
          "je": "cueillerais",
          "tu": "cueillerais",
          "il/elle": "cueillerait",
          "nous": "cueillerions",
          "vous": "cueilleriez",
          "ils/elles": "cueilleraient"
        },
        "plus-que-parfait": {
          "j'": "avais cueilli",
          "tu": "avais cueilli",
          "il/elle": "avait cueilli",
          "nous": "avions cueilli",
          "vous": "aviez cueilli",
          "ils/elles": "avaient cueilli"
        },
        "passé antérieur": {
          "j'": "eus cueilli",
          "tu": "eus cueilli",
          "il/elle": "eut cueilli",
          "nous": "eûmes cueilli",
          "vous": "eûtes cueilli",
          "ils/elles": "eurent cueilli"
        },
        "futur antérieur": {
          "je": "aurai cueilli",
          "tu": "auras cueilli",
          "il/elle": "aura cueilli",
          "nous": "aurons cueilli",
          "vous": "aurez cueilli",
          "ils/elles": "auront cueilli"
        },
        "conditionnel passé première forme": {
          "je": "aurais cueilli",
          "tu": "aurais cueilli",
          "il/elle": "aurait cueilli",
          "nous": "aurions cueilli",
          "vous": "auriez cueilli",
          "ils/elles": "auraient cueilli"
        }
      }
    },
    {
      "infinitive": "frémir",
      "conjugations": {
        "présent": {
          "je": "frémis",
          "tu": "frémis",
          "il/elle": "frémit",
          "nous": "frémissons",
          "vous": "frémissez",
          "ils/elles": "frémissent"
        },
        "passé composé": {
          "j'": "ai frémi",
          "tu": "as frémi",
          "il/elle": "a frémi",
          "nous": "avons frémi",
          "vous": "avez frémi",
          "ils/elles": "ont frémi"
        },
        "imparfait": {
          "je": "frémissais",
          "tu": "frémissais",
          "il/elle": "frémissait",
          "nous": "frémissions",
          "vous": "frémissiez",
          "ils/elles": "frémissaient"
        },
        "passé simple": {
          "je": "frémis",
          "tu": "frémis",
          "il/elle": "frémit",
          "nous": "frémîmes",
          "vous": "frémîtes",
          "ils/elles": "frémirent"
        },
        "futur simple": {
          "je": "frémirai",
          "tu": "frémiras",
          "il/elle": "frémira",
          "nous": "frémirons",
          "vous": "frémirez",
          "ils/elles": "frémiront"
        },
        "imparfait du subjonctif": {
          "que je": "frémisse",
          "que tu": "frémisses",
          "qu'il/elle": "frémît",
          "que nous": "frémissions",
          "que vous": "frémissiez",
          "qu'ils/elles": "frémissent"
        },
        "subjonctif passé": {
          "que je": "aie frémi",
          "que tu": "aies frémi",
          "qu'il/elle": "ait frémi",
          "que nous": "ayons frémi",
          "que vous": "ayez frémi",
          "qu'ils/elles": "aient frémi"
        },
        "conditionnel présent": {
          "je": "frémirais",
          "tu": "frémirais",
          "il/elle": "frémirait",
          "nous": "frémirions",
          "vous": "frémiriez",
          "ils/elles": "frémiraient"
        },
        "plus-que-parfait": {
          "j'": "avais frémi",
          "tu": "avais frémi",
          "il/elle": "avait frémi",
          "nous": "avions frémi",
          "vous": "aviez frémi",
          "ils/elles": "avaient frémi"
        },
        "passé antérieur": {
          "j'": "eus frémi",
          "tu": "eus frémi",
          "il/elle": "eut frémi",
          "nous": "eûmes frémi",
          "vous": "eûtes frémi",
          "ils/elles": "eurent frémi"
        },
        "futur antérieur": {
          "je": "aurai frémi",
          "tu": "auras frémi",
          "il/elle": "aura frémi",
          "nous": "aurons frémi",
          "vous": "aurez frémi",
          "ils/elles": "auront frémi"
        },
        "conditionnel passé première forme": {
          "je": "aurais frémi",
          "tu": "aurais frémi",
          "il/elle": "aurait frémi",
          "nous": "aurions frémi",
          "vous": "auriez frémi",
          "ils/elles": "auraient frémi"
        }
      }
    },
    {
      "infinitive": "tordre",
      "conjugations": {
        "présent": {
          "je": "tords",
          "tu": "tords",
          "il/elle": "tord",
          "nous": "tordons",
          "vous": "tordez",
          "ils/elles": "tordent"
        },
        "passé composé": {
          "j'": "ai tordu",
          "tu": "as tordu",
          "il/elle": "a tordu",
          "nous": "avons tordu",
          "vous": "avez tordu",
          "ils/elles": "ont tordu"
        },
        "imparfait": {
          "je": "tordais",
          "tu": "tordais",
          "il/elle": "tordait",
          "nous": "tordions",
          "vous": "tordiez",
          "ils/elles": "tordaient"
        },
        "passé simple": {
          "je": "tordis",
          "tu": "tordis",
          "il/elle": "tordit",
          "nous": "tordîmes",
          "vous": "tordîtes",
          "ils/elles": "tordirent"
        },
        "futur simple": {
          "je": "tordrai",
          "tu": "tordras",
          "il/elle": "tordra",
          "nous": "tordrons",
          "vous": "tordrez",
          "ils/elles": "tordront"
        },
        "imparfait du subjonctif": {
          "que je": "tordisse",
          "que tu": "tordisses",
          "qu'il/elle": "tordît",
          "que nous": "tordissions",
          "que vous": "tordissiez",
          "qu'ils/elles": "tordissent"
        },
        "subjonctif passé": {
          "que je": "aie tordu",
          "que tu": "aies tordu",
          "qu'il/elle": "ait tordu",
          "que nous": "ayons tordu",
          "que vous": "ayez tordu",
          "qu'ils/elles": "aient tordu"
        },
        "conditionnel présent": {
          "je": "tordrais",
          "tu": "tordrais",
          "il/elle": "tordrait",
          "nous": "tordrions",
          "vous": "tordriez",
          "ils/elles": "tordraient"
        },
        "plus-que-parfait": {
          "j'": "avais tordu",
          "tu": "avais tordu",
          "il/elle": "avait tordu",
          "nous": "avions tordu",
          "vous": "aviez tordu",
          "ils/elles": "avaient tordu"
        },
        "passé antérieur": {
          "j'": "eus tordu",
          "tu": "eus tordu",
          "il/elle": "eut tordu",
          "nous": "eûmes tordu",
          "vous": "eûtes tordu",
          "ils/elles": "eurent tordu"
        },
        "futur antérieur": {
          "je": "aurai tordu",
          "tu": "auras tordu",
          "il/elle": "aura tordu",
          "nous": "aurons tordu",
          "vous": "aurez tordu",
          "ils/elles": "auront tordu"
        },
        "conditionnel passé première forme": {
          "je": "aurais tordu",
          "tu": "aurais tordu",
          "il/elle": "aurait tordu",
          "nous": "aurions tordu",
          "vous": "auriez tordu",
          "ils/elles": "auraient tordu"
        }
      }
    },
    {
      "infinitive": "pouvoir",
      "conjugations": {
        "présent": {
          "je": "peux",
          "tu": "peux",
          "il/elle": "peut",
          "nous": "pouvons",
          "vous": "pouvez",
          "ils/elles": "peuvent"
        },
        "passé composé": {
          "je": "ai pu",
          "tu": "as pu",
          "il/elle": "a pu",
          "nous": "avons pu",
          "vous": "avez pu",
          "ils/elles": "ont pu"
        },
        "imparfait": {
          "je": "pouvais",
          "tu": "pouvais",
          "il/elle": "pouvait",
          "nous": "pouvions",
          "vous": "pouviez",
          "ils/elles": "pouvaient"
        },
        "passé simple": {
          "je": "pus",
          "tu": "pus",
          "il/elle": "put",
          "nous": "pûmes",
          "vous": "pûtes",
          "ils/elles": "purent"
        },
        "futur simple": {
          "je": "pourrai",
          "tu": "pourras",
          "il/elle": "pourra",
          "nous": "pourrons",
          "vous": "pourrez",
          "ils/elles": "pourront"
        },
        "imparfait du subjonctif": {
          "que je": "pusse",
          "que tu": "pusses",
          "qu'il/elle": "pût",
          "que nous": "pusions",
          "que vous": "pussiez",
          "qu'ils/elles": "pussent"
        },
        "subjonctif passé": {
          "que j'": "aie pu",
          "que tu": "aies pu",
          "qu'il/elle": "ait pu",
          "que nous": "ayons pu",
          "que vous": "ayez pu",
          "qu'ils/elles": "aient pu"
        },
        "conditionnel présent": {
          "je": "pourrais",
          "tu": "pourrais",
          "il/elle": "pourrait",
          "nous": "pourrions",
          "vous": "pourriez",
          "ils/elles": "pourraient"
        },
        "plus-que-parfait": {
          "j'": "avais pu",
          "tu": "avais pu",
          "il/elle": "avait pu",
          "nous": "avions pu",
          "vous": "aviez pu",
          "ils/elles": "avaient pu"
        },
        "passé antérieur": {
          "j'": "eus pu",
          "tu": "eus pu",
          "il/elle": "eut pu",
          "nous": "eûmes pu",
          "vous": "eûtes pu",
          "ils/elles": "eurent pu"
        },
        "futur antérieur": {
          "j'": "aurai pu",
          "tu": "auras pu",
          "il/elle": "aura pu",
          "nous": "aurons pu",
          "vous": "aurez pu",
          "ils/elles": "auront pu"
        },
        "conditionnel passé première forme": {
          "j'": "aurais pu",
          "tu": "aurais pu",
          "il/elle": "aurait pu",
          "nous": "aurions pu",
          "vous": "auriez pu",
          "ils/elles": "auraient pu"
        }
      }
    }
  ]
}
